databaselib/__init__.py
databaselib/databaseDevFriendlyAbstraction.py
databaselib/etodatabaselib.py
databaselib/etohashlib.py
databaselib/helper.py
eto_mysql_databaselib-1.1.5.dist-info/LICENSE
eto_mysql_databaselib-1.1.5.dist-info/METADATA
eto_mysql_databaselib-1.1.5.dist-info/WHEEL
eto_mysql_databaselib-1.1.5.dist-info/top_level.txt
eto_mysql_databaselib-1.1.5.dist-info/RECORD
