Metadata-Version: 2.1
Name: eto-mysql-databaselib
Version: 1.1.5
Summary: A library with the sole purpose of making connections to mysql databases easier
Author-email: Eto_chan <etochandev@gmail.com>
License: MIT License
Project-URL: Homepage, https://github.com/Etozinhachan/eto-mysql-databaselib
Keywords: database,mysql
Classifier: License :: OSI Approved :: MIT License
Classifier: Programming Language :: Python
Classifier: Programming Language :: Python :: 3
Requires-Python: >=3.12
License-File: LICENSE
Requires-Dist: pymysql
Requires-Dist: cryptography
Requires-Dist: pyargon2
